setup.py
probability_distributions_q4l/Binomialdistribution.py
probability_distributions_q4l/Gaussiandistribution.py
probability_distributions_q4l/Generaldistribution.py
probability_distributions_q4l/__init__.py
probability_distributions_q4l.egg-info/PKG-INFO
probability_distributions_q4l.egg-info/SOURCES.txt
probability_distributions_q4l.egg-info/dependency_links.txt
probability_distributions_q4l.egg-info/not-zip-safe
probability_distributions_q4l.egg-info/top_level.txt