Metadata-Version: 2.1
Name: probability-distributions-q4l
Version: 2
Summary: Gaussian distributions
